helpers_mbk/__init__.py
helpers_mbk/__main__.py
helpers_mbk/helpers.py
helpers_mbk-1.0.1.dist-info/LICENSE
helpers_mbk-1.0.1.dist-info/METADATA
helpers_mbk-1.0.1.dist-info/WHEEL
helpers_mbk-1.0.1.dist-info/entry_points.txt
helpers_mbk-1.0.1.dist-info/top_level.txt
helpers_mbk-1.0.1.dist-info/RECORD
