Metadata-Version: 2.1
Name: helpers-mbk
Version: 1.0.1
Summary: Some functions that Muhammed Buyukkinaci uses a lot
Author-email: Muhammed Buyukkinaci <muhammedbuyukkinaci@gmail.com>
License: MIT License
Project-URL: Homepage, https://github.com/MuhammedBuyukkinaci/helpers-mbk
Keywords: feed,reader,tutorial
Classifier: License :: OSI Approved :: MIT License
Classifier: Programming Language :: Python
Classifier: Programming Language :: Python :: 3
Requires-Python: >=3.8
License-File: LICENSE
Requires-Dist: pandas (>=2.0.0)
Requires-Dist: numpy (>=1.24.2)
Provides-Extra: dev
Requires-Dist: pytest ; extra == 'dev'
